vidownloader/__init__.py
vidownloader/__main__.py
vidownloader/main.py
vidownloader/resources.qrc
vidownloader/core/Constants.py
vidownloader/core/Logger.py
vidownloader/core/Models.py
vidownloader/core/Utils.py
vidownloader/core/VIIO.py
vidownloader/core/VSettings.py
vidownloader/core/__init__.py
vidownloader/core/http.py
vidownloader/core/Worker/Downloader.py
vidownloader/core/Worker/Parser.py
vidownloader/core/Worker/Scraper.py
vidownloader/core/Worker/__init__.py
vidownloader/fonts/Poppins-Medium.ttf
vidownloader/fonts/Poppins-Regular.ttf
vidownloader/fonts/Poppins-SemiBold.ttf
vidownloader/icons/icon.ico
vidownloader/icons/icon.png
vidownloader/ui/__init__.py
vidownloader/ui/dialogs.py
vidownloader/ui/home_ui.py
vidownloader/ui/main_ui.py
vidownloader/ui/resources_rc.py
vidownloader/ui/stylesheets.py
vidownloader/window/HomeWindow.py
vidownloader/window/MainWindow.py
vidownloader/window/__init__.py
vidownloader-1.0.0b2.dist-info/METADATA
vidownloader-1.0.0b2.dist-info/WHEEL
vidownloader-1.0.0b2.dist-info/entry_points.txt
vidownloader-1.0.0b2.dist-info/licenses/LICENSE
vidownloader-1.0.0b2.dist-info/RECORD
