Metadata-Version: 2.4
Name: vidownloader
Version: 1.0.0b2
Summary: A modern YouTube video downloader with a beautiful PyQt5 interface
Project-URL: Homepage, https://github.com/farhaanaliii/vidownloader
Project-URL: Repository, https://github.com/farhaanaliii/vidownloader
Project-URL: Issues, https://github.com/farhaanaliii/vidownloader/issues
Author-email: Farhan Ali <i.farhanali.de@gmail.com>
License-Expression: MIT
License-File: LICENSE
Keywords: downloader,pyqt5,video,youtube,yt-dlp
Classifier: Development Status :: 4 - Beta
Classifier: Environment :: X11 Applications :: Qt
Classifier: Intended Audience :: End Users/Desktop
Classifier: License :: OSI Approved :: MIT License
Classifier: Operating System :: OS Independent
Classifier: Programming Language :: Python :: 3
Classifier: Programming Language :: Python :: 3.9
Classifier: Programming Language :: Python :: 3.10
Classifier: Programming Language :: Python :: 3.11
Classifier: Programming Language :: Python :: 3.12
Classifier: Topic :: Multimedia :: Video
Requires-Python: >=3.9
Requires-Dist: curl-cffi
Requires-Dist: pyqt5>=5.15.11
Requires-Dist: yt-dlp
Provides-Extra: dev
Requires-Dist: pytest-cov>=7.0.0; extra == 'dev'
Requires-Dist: pytest-qt>=4.2.0; extra == 'dev'
Requires-Dist: pytest>=9.0.2; extra == 'dev'
